__init__.py
gofile_uploader.py
gofile_uploader/__init__.py
gofile_uploader/api.py
gofile_uploader/cli.py
gofile_uploader/conftest.py
gofile_uploader/gofile_uploader.py
gofile_uploader/types.py
gofile_uploader/utils.py
gofile_uploader/tests/test_api_account.py
gofile_uploader/tests/test_api_folder.py
gofile_uploader/tests/test_api_get_content.py
gofile_uploader/tests/test_api_servers.py
gofile_uploader/tests/test_api_update_content.py
gofile_uploader/tests/test_api_upload_file.py
gofile_uploader/tests/test_api_wt.py
gofile_uploader/tests/test_cli.py
gofile_uploader/tests/test_client_folder.py
gofile_uploader/tests/test_client_upload.py
gofileiouploader-0.13.3.dist-info/licenses/LICENSE
gofileiouploader-0.13.3.dist-info/METADATA
gofileiouploader-0.13.3.dist-info/WHEEL
gofileiouploader-0.13.3.dist-info/entry_points.txt
gofileiouploader-0.13.3.dist-info/top_level.txt
gofileiouploader-0.13.3.dist-info/RECORD
