Metadata-Version: 2.4
Name: GofileIOUploader
Version: 0.13.3
Summary: Gofile.io uploader supporting parallel uploads
Author-email: Alex Mi <alexmi3.14@gmail.com>
Maintainer-email: Alex Mi <alexmi3.14@gmail.com>
License: MIT License
Project-URL: Homepage, https://github.com/alexmi256/gofile-uploader
Project-URL: Repository, https://github.com/alexmi256/gofile-uploader.git
Project-URL: Service, https://gofile.io
Project-URL: Gofile API, https://gofile.io/api
Keywords: gofile,upload,storage,parallel
Classifier: Development Status :: 4 - Beta
Classifier: Environment :: Console
Classifier: Framework :: aiohttp
Classifier: License :: OSI Approved :: MIT License
Classifier: Intended Audience :: End Users/Desktop
Classifier: Programming Language :: Python :: 3.9
Classifier: Programming Language :: Python :: Implementation
Classifier: Topic :: Internet
Classifier: Topic :: Utilities
Requires-Python: >=3.9
License-File: LICENSE
Requires-Dist: aiohttp
Requires-Dist: tqdm
Requires-Dist: typing-extensions
Dynamic: license-file
